shashwat_shukla/Shashwat_CV.pdf
shashwat_shukla/__init__.py
shashwat_shukla/cli.py
shashwat_shukla-0.1.4.dist-info/METADATA
shashwat_shukla-0.1.4.dist-info/WHEEL
shashwat_shukla-0.1.4.dist-info/entry_points.txt
shashwat_shukla-0.1.4.dist-info/top_level.txt
shashwat_shukla-0.1.4.dist-info/RECORD
