Metadata-Version: 2.4
Name: shashwat-shukla
Version: 0.1.4
Summary: Personal developer CLI by Shashwat Shukla
Author: Shashwat Shukla
Keywords: resume,cli,developer,profile
Requires-Python: >=3.9
Requires-Dist: qrcode[pil]
